PyQt6/Qt6/qsci/api/python/PyQt6-DataVisualization.api
PyQt6/QtDataVisualization.abi3.so
PyQt6/QtDataVisualization.pyi
PyQt6/bindings/QtDataVisualization/QtDataVisualization.toml
PyQt6/bindings/QtDataVisualization/QtDataVisualizationmod.sip
PyQt6/bindings/QtDataVisualization/q3dbars.sip
PyQt6/bindings/QtDataVisualization/q3dcamera.sip
PyQt6/bindings/QtDataVisualization/q3dinputhandler.sip
PyQt6/bindings/QtDataVisualization/q3dlight.sip
PyQt6/bindings/QtDataVisualization/q3dobject.sip
PyQt6/bindings/QtDataVisualization/q3dscatter.sip
PyQt6/bindings/QtDataVisualization/q3dscene.sip
PyQt6/bindings/QtDataVisualization/q3dsurface.sip
PyQt6/bindings/QtDataVisualization/q3dtheme.sip
PyQt6/bindings/QtDataVisualization/qabstract3daxis.sip
PyQt6/bindings/QtDataVisualization/qabstract3dgraph.sip
PyQt6/bindings/QtDataVisualization/qabstract3dinputhandler.sip
PyQt6/bindings/QtDataVisualization/qabstract3dseries.sip
PyQt6/bindings/QtDataVisualization/qabstractdataproxy.sip
PyQt6/bindings/QtDataVisualization/qbar3dseries.sip
PyQt6/bindings/QtDataVisualization/qbardataitem.sip
PyQt6/bindings/QtDataVisualization/qbardataproxy.sip
PyQt6/bindings/QtDataVisualization/qcategory3daxis.sip
PyQt6/bindings/QtDataVisualization/qcustom3ditem.sip
PyQt6/bindings/QtDataVisualization/qcustom3dlabel.sip
PyQt6/bindings/QtDataVisualization/qcustom3dvolume.sip
PyQt6/bindings/QtDataVisualization/qheightmapsurfacedataproxy.sip
PyQt6/bindings/QtDataVisualization/qitemmodelbardataproxy.sip
PyQt6/bindings/QtDataVisualization/qitemmodelscatterdataproxy.sip
PyQt6/bindings/QtDataVisualization/qitemmodelsurfacedataproxy.sip
PyQt6/bindings/QtDataVisualization/qlist.sip
PyQt6/bindings/QtDataVisualization/qlogvalue3daxisformatter.sip
PyQt6/bindings/QtDataVisualization/qscatter3dseries.sip
PyQt6/bindings/QtDataVisualization/qscatterdataitem.sip
PyQt6/bindings/QtDataVisualization/qscatterdataproxy.sip
PyQt6/bindings/QtDataVisualization/qsurface3dseries.sip
PyQt6/bindings/QtDataVisualization/qsurfacedataitem.sip
pyqt6_datavisualization-6.10.0.dist-info/licenses/LICENSE
pyqt6_datavisualization-6.10.0.dist-info/WHEEL
pyqt6_datavisualization-6.10.0.dist-info/METADATA
pyqt6_datavisualization-6.10.0.dist-info/RECORD
